{
    "puzzle_1": {
        "text_description": "There are five houses. The Englishman lives in the red house. The Spaniard owns the dog. Coffee is drunk in the green house. The Ukrainian drinks tea. The green house is immediately to the right of the ivory house. The Old Gold smoker owns snails. Kools are smoked in the yellow house. Milk is drunk in the middle house. The Norwegian lives in the first house. The man who smokes Chesterfields lives in the house next to the man with the fox. Kools are smoked in the house next to the house where the horse is kept. The Lucky Strike smoker drinks orange juice. The Japanese smokes Parliaments. The Norwegian lives next to the blue house. Now, who drinks water? Who owns the zebra?",
        "z3_format": {
            "houses_count": 5,
            "categories": {
                "nationalities": ["Englishman", "Spaniard", "Ukrainian", "Norwegian", "Japanese"],
                "colors": ["Red", "Green", "Ivory", "Blue", "Yellow"],
                "pets": ["Fox", "Horse", "Zebra", "Dog", "Snails"],
                "drinks": ["Coffee", "Milk", "OrangeJuice", "Tea", "Water"],
                "cigarettes": ["Parliaments", "Kools", "LuckyStrike", "OldGold", "Chesterfields"]
            },
            "constraints": [
                {
                    "type": "distinct_categories",
                    "categories": [
                        "nationalities",
                        "colors",
                        "pets",
                        "drinks",
                        "cigarettes"
                    ]
                },
                {
                    "type": "range",
                    "from": 1,
                    "to": 5
                },
                {"type": "eq", "var1": "Englishman", "var2": "Red"},
                {"type": "eq", "var1": "Spaniard", "var2": "Dog"},
                {"type": "eq", "var1": "Coffee", "var2": "Green"},
                {"type": "eq", "var1": "Ukrainian", "var2": "Tea"},
                {"type": "eq_offset", "var1": "Green", "var2": "Ivory", "offset": 1},
                {"type": "eq", "var1": "OldGold", "var2": "Snails"},
                {"type": "eq", "var1": "Kools", "var2": "Yellow"},
                {"type": "eq", "var1": "Milk", "var2int": 3},
                {"type": "eq", "var1": "Norwegian", "var2int": 1},
                {"type": "neighbor", "var1": "Chesterfields", "var2": "Fox"},
                {"type": "neighbor", "var1": "Kools", "var2": "Horse"},
                {"type": "eq", "var1": "LuckyStrike", "var2": "OrangeJuice"},
                {"type": "eq", "var1": "Japanese", "var2": "Parliaments"},
                {"type": "neighbor", "var1": "Norwegian", "var2": "Blue"}
            ]
        },
        "ground_truth": {
            "houses": [
                {
                    "House": 1,
                    "Nationality": "Norwegian",
                    "Color": "Yellow",
                    "Pet": "Fox",
                    "Drink": "Water",
                    "Cigarette": "Kools"
                },
                {
                    "House": 2,
                    "Nationality": "Ukrainian",
                    "Color": "Blue",
                    "Pet": "Horse",
                    "Drink": "Tea",
                    "Cigarette": "Chesterfields"
                },
                {
                    "House": 3,
                    "Nationality": "Englishman",
                    "Color": "Red",
                    "Pet": "Snails",
                    "Drink": "Milk",
                    "Cigarette": "OldGold"
                },
                {
                    "House": 4,
                    "Nationality": "Japanese",
                    "Color": "Green",
                    "Pet": "Zebra",
                    "Drink": "Coffee",
                    "Cigarette": "Parliaments"
                },
                {
                    "House": 5,
                    "Nationality": "Spaniard",
                    "Color": "Ivory",
                    "Pet": "Dog",
                    "Drink": "OrangeJuice",
                    "Cigarette": "LuckyStrike"
                }
            ]
        }
    },

    "puzzle_2": {
        "text_description": "There are two houses. One is red, the other is blue. Person A lives in the red house, and Person B lives in the blue house. Who lives in each house?",
        "z3_format": {
            "houses_count": 2,
            "categories": {
                "colors": ["Red", "Blue"],
                "people": ["PersonA", "PersonB"]
            },
            "constraints": [
                {
                    "type": "distinct_categories",
                    "categories": ["colors", "people"]
                },
                {
                    "type": "range",
                    "from": 1,
                    "to": 2
                },
                {"type": "eq", "var1": "PersonA", "var2": "Red"},
                {"type": "eq", "var1": "PersonB", "var2": "Blue"}
            ]
        },
        "ground_truth": {
            "houses": [
                {
                    "House": 1,
                    "Person": "A",
                    "Color": "Red"
                },
                {
                    "House": 2,
                    "Person": "B",
                    "Color": "Blue"
                }
            ]
        }
    },

    "puzzle_3": {
        "text_description": "There are 3 houses, numbered 1 to 3 from left to right. Each house is occupied by a different person. Each house has a unique attribute for each characteristic:\n- Names: Peter, Eric, Arnold\n- Drinks: tea, water, milk\n\n## Clues\n1. Peter is in the second house.\n2. Arnold is directly left of the one who only drinks water.\n3. The one who only drinks water is directly left of the person who likes milk.\n\nWe want to know who lives in each house and who drinks what.",
        "z3_format": {
            "houses_count": 3,
            "categories": {
                "names": ["Peter", "Eric", "Arnold"],
                "drinks": ["tea", "water", "milk"]
            },
            "constraints": [
                {
                    "type": "distinct_categories",
                    "categories": ["names", "drinks"]
                },
                {
                    "type": "range",
                    "from": 1,
                    "to": 3
                },
                { "type": "eq", "var1": "Peter", "var2int": 2 },
                {
                    "type": "eq_offset",
                    "var1": "water",
                    "var2": "Arnold",
                    "offset": 1
                },
                {
                    "type": "eq_offset",
                    "var1": "milk",
                    "var2": "water",
                    "offset": 1
                }
            ]
        },
        "ground_truth": {
            "houses": [
                {
                    "House": 1,
                    "Name": "Arnold",
                    "Drink": "tea"
                },
                {
                    "House": 2,
                    "Name": "Peter",
                    "Drink": "water"
                },
                {
                    "House": 3,
                    "Name": "Eric",
                    "Drink": "milk"
                }
            ]
        }
    },

    "puzzle_4": {
        "text_description": "There are 4 houses in a row, numbered 1 to 4 (left to right). Each house is occupied by a different person and has unique attributes: names (Eric, Arnold, Alice, Peter), mothers (Holly, Kailyn, Aniya, Janelle), birthdays (april, feb, sept, jan), and house styles (ranch, colonial, victorian, craftsman).\n\nClues:\n1. Peter is the person whose birthday is in February.\n2. The person whose birthday is in February is not in the fourth house.\n3. The person whose birthday is in January is somewhere to the right of the person in a ranch-style home.\n4. The person whose birthday is in January is directly left of Eric.\n5. The person in a ranch-style home is the person whose birthday is in April.\n6. The person whose mother's name is Janelle is the person whose birthday is in September.\n7. The person in a ranch-style home and the person whose mother's name is Kailyn are next to each other.\n8. Arnold is the person whose mother's name is Holly.\n9. The person whose mother's name is Kailyn is directly left of the person residing in a Victorian house.\n10. The person whose birthday is in January is the person in a Craftsman-style house.\n",
        "z3_format": {
            "houses_count": 4,
            "categories": {
                "names": ["Eric", "Arnold", "Alice", "Peter"],
                "mothers": ["Holly", "Kailyn", "Aniya", "Janelle"],
                "birthdays": ["april", "feb", "sept", "jan"],
                "house_styles": ["ranch", "colonial", "victorian", "craftsman"]
            },
            "constraints": [
                {
                    "type": "distinct_categories",
                    "categories": ["names", "mothers", "birthdays", "house_styles"]
                },
                {
                    "type": "range",
                    "from": 1,
                    "to": 4
                },
                { "type": "eq", "var1": "Peter", "var2": "feb" },
                { "type": "neq", "var1": "feb", "var2int": 4 },
                { "type": "left", "var1": "ranch", "var2": "jan" },
                { "type": "eq_offset", "var1": "Eric", "var2": "jan", "offset": 1 },
                { "type": "eq", "var1": "ranch", "var2": "april" },
                { "type": "eq", "var1": "Janelle", "var2": "sept" },
                { "type": "neighbor", "var1": "ranch", "var2": "Kailyn" },
                { "type": "eq", "var1": "Arnold", "var2": "Holly" },
                { "type": "eq_offset", "var1": "victorian", "var2": "Kailyn", "offset": 1 },
                { "type": "eq", "var1": "jan", "var2": "craftsman" }
            ]
        },
        "ground_truth": {
            "houses": [
                {
                    "House": 1,
                    "Name": "Peter",
                    "Mother": "Aniya",
                    "Birthday": "feb",
                    "HouseStyle": "colonial"
                },
                {
                    "House": 2,
                    "Name": "Arnold",
                    "Mother": "Holly",
                    "Birthday": "april",
                    "HouseStyle": "ranch"
                },
                {
                    "House": 3,
                    "Name": "Alice",
                    "Mother": "Kailyn",
                    "Birthday": "jan",
                    "HouseStyle": "craftsman"
                },
                {
                    "House": 4,
                    "Name": "Eric",
                    "Mother": "Janelle",
                    "Birthday": "sept",
                    "HouseStyle": "victorian"
                }
            ]
        }
    }
}
